<?xml version="1.0" encoding="UTF-8"?>
<!DOCTYPE suite SYSTEM "http://testng.org/testng-1.0.dtd">
<suite name="All Test Suite">

    <listeners>
        <listener class-name="utilities.ExtentReportManager"></listener>
    </listeners>
    <test verbose="2" preserve-order="true" name="Linux-Chrome">

        <parameter name="os" value="Linux"></parameter>
        <parameter name="browser" value="chrome"></parameter>
        <classes>
            <class name="testCases.TC001_AccountRegistrationTest"></class>
            <class name="testCases.TC002LoginTest"></class>
        </classes>
    </test>
</suite>